CHANGELOG
LICENSE
MANIFEST.in
README.md
VERSION
pyproject.toml
setup.py
src/isoduration/__init__.py
src/isoduration/constants.py
src/isoduration/types.py
src/isoduration.egg-info/PKG-INFO
src/isoduration.egg-info/SOURCES.txt
src/isoduration.egg-info/dependency_links.txt
src/isoduration.egg-info/not-zip-safe
src/isoduration.egg-info/requires.txt
src/isoduration.egg-info/top_level.txt
src/isoduration/formatter/__init__.py
src/isoduration/formatter/checking.py
src/isoduration/formatter/exceptions.py
src/isoduration/formatter/formatting.py
src/isoduration/operations/__init__.py
src/isoduration/operations/util.py
src/isoduration/parser/__init__.py
src/isoduration/parser/exceptions.py
src/isoduration/parser/parsing.py
src/isoduration/parser/util.py