Metadata-Version: 2.1
Name: isoduration
Version: 20.11.0
Summary: Operations with ISO 8601 durations
Home-page: https://github.com/bolsote/isoduration
Author: Víctor Muñoz
Author-email: victorm@marshland.es
License: UNKNOWN
Project-URL: Repository, https://github.com/bolsote/isoduration
Project-URL: Bug Reports, https://github.com/bolsote/isoduration/issues
Project-URL: Changelog, https://github.com/bolsote/isoduration/blob/master/CHANGELOG
Keywords: datetime,date,time,duration,duration-parsing,duration-string,iso8601,iso8601-duration
Platform: UNKNOWN
Classifier: Programming Language :: Python :: 3
Classifier: Operating System :: OS Independent
Classifier: License :: OSI Approved :: ISC License (ISCL)
Classifier: Development Status :: 4 - Beta
Classifier: Intended Audience :: Developers
Classifier: Topic :: Software Development :: Libraries :: Python Modules
Requires-Python: >=3.7
